{
    "000": {
        "cont": 0.0,
        "phi num": "000"
    },
    "001": {
        "cont": -0.00047845451560824795,
        "phi num": "001"
    },
    "002": {
        "cont": -0.003791646473152447,
        "phi num": "002"
    },
    "003": {
        "cont": -0.0018091908809903146,
        "phi num": "003"
    },
    "004": {
        "cont": -0.002159266637322457,
        "phi num": "004"
    },
    "005": {
        "cont": 0.000530003192707638,
        "phi num": "005"
    },
    "006": {
        "cont": 0.0006360176471285685,
        "phi num": "006"
    },
    "007": {
        "cont": -0.0004605913161822862,
        "phi num": "007"
    },
    "008": {
        "cont": 0.000490100466475377,
        "phi num": "008"
    },
    "009": {
        "cont": 0.00030540210694429134,
        "phi num": "009"
    },
    "010": {
        "cont": -6.89466083114757e-05,
        "phi num": "010"
    },
    "011": {
        "cont": -7.037110316200657e-05,
        "phi num": "011"
    },
    "012": {
        "cont": 6.399224247740534e-05,
        "phi num": "012"
    },
    "013": {
        "cont": 3.664875730353609e-05,
        "phi num": "013"
    },
    "014": {
        "cont": -7.136801879572753e-06,
        "phi num": "014"
    },
    "015": {
        "cont": 4.258521462479922e-05,
        "phi num": "015"
    },
    "016": {
        "cont": -3.778077277389833e-05,
        "phi num": "016"
    },
    "017": {
        "cont": 5.840216438996498e-06,
        "phi num": "017"
    },
    "018": {
        "cont": -5.238023771613755e-05,
        "phi num": "018"
    },
    "019": {
        "cont": 5.7838541607626434e-06,
        "phi num": "019"
    },
    "020": {
        "cont": -3.9612930309130336e-05,
        "phi num": "020"
    },
    "021": {
        "cont": 1.5120148415008857e-05,
        "phi num": "021"
    },
    "022": {
        "cont": 1.2648090973283999e-05,
        "phi num": "022"
    },
    "023": {
        "cont": 3.29786376255903e-05,
        "phi num": "023"
    },
    "024": {
        "cont": 4.269953726872512e-05,
        "phi num": "024"
    },
    "025": {
        "cont": 0.0,
        "phi num": "025"
    },
    "026": {
        "cont": 9.60710839970848e-05,
        "phi num": "026"
    },
    "027": {
        "cont": -7.628267361058811e-06,
        "phi num": "027"
    },
    "028": {
        "cont": -2.1206725153218255e-05,
        "phi num": "028"
    },
    "029": {
        "cont": 0.0,
        "phi num": "029"
    },
    "030": {
        "cont": -4.8162608691586756e-05,
        "phi num": "030"
    },
    "031": {
        "cont": 5.076522810817946e-05,
        "phi num": "031"
    },
    "032": {
        "cont": 8.865795742737289e-05,
        "phi num": "032"
    },
    "033": {
        "cont": 4.736224365661501e-05,
        "phi num": "033"
    },
    "034": {
        "cont": -5.858247832516319e-05,
        "phi num": "034"
    },
    "035": {
        "cont": -3.405807333882291e-05,
        "phi num": "035"
    },
    "036": {
        "cont": -0.00011229062235476082,
        "phi num": "036"
    },
    "037": {
        "cont": -4.987413711623826e-05,
        "phi num": "037"
    },
    "038": {
        "cont": 0.00017967435865019304,
        "phi num": "038"
    },
    "039": {
        "cont": 0.00011295861541862143,
        "phi num": "039"
    },
    "040": {
        "cont": 0.00010222256505625797,
        "phi num": "040"
    },
    "041": {
        "cont": 0.00012383422509410874,
        "phi num": "041"
    },
    "042": {
        "cont": 0.00010356259839074858,
        "phi num": "042"
    },
    "043": {
        "cont": 4.751007458731963e-05,
        "phi num": "043"
    },
    "044": {
        "cont": -1.5563941279748102e-05,
        "phi num": "044"
    },
    "045": {
        "cont": 7.70003480413871e-05,
        "phi num": "045"
    },
    "046": {
        "cont": 5.6188142952871286e-05,
        "phi num": "046"
    },
    "047": {
        "cont": -4.875121355011408e-05,
        "phi num": "047"
    },
    "048": {
        "cont": -4.808224793768236e-05,
        "phi num": "048"
    },
    "049": {
        "cont": 1.1884585211507654e-08,
        "phi num": "049"
    },
    "050": {
        "cont": 0.00010147593761694962,
        "phi num": "050"
    },
    "051": {
        "cont": 0.0,
        "phi num": "051"
    },
    "052": {
        "cont": 9.380780189076691e-05,
        "phi num": "052"
    },
    "053": {
        "cont": 3.512639518727345e-06,
        "phi num": "053"
    },
    "054": {
        "cont": 0.00011008117593938412,
        "phi num": "054"
    },
    "055": {
        "cont": 5.67788487492898e-05,
        "phi num": "055"
    },
    "056": {
        "cont": -2.641431899928109e-05,
        "phi num": "056"
    },
    "057": {
        "cont": 0.0,
        "phi num": "057"
    },
    "058": {
        "cont": 4.2122507632275036e-05,
        "phi num": "058"
    },
    "059": {
        "cont": 0.0,
        "phi num": "059"
    },
    "060": {
        "cont": 5.1461404903722775e-05,
        "phi num": "060"
    },
    "061": {
        "cont": 0.0,
        "phi num": "061"
    },
    "062": {
        "cont": 7.183120571174607e-05,
        "phi num": "062"
    },
    "063": {
        "cont": 4.137602892731388e-05,
        "phi num": "063"
    },
    "064": {
        "cont": 4.8197256308636674e-05,
        "phi num": "064"
    },
    "065": {
        "cont": 5.14596931323194e-05,
        "phi num": "065"
    },
    "066": {
        "cont": 4.439605681286087e-05,
        "phi num": "066"
    },
    "067": {
        "cont": 0.0,
        "phi num": "067"
    },
    "068": {
        "cont": 4.659596686532323e-05,
        "phi num": "068"
    },
    "069": {
        "cont": 0.0,
        "phi num": "069"
    },
    "070": {
        "cont": 0.0,
        "phi num": "070"
    },
    "071": {
        "cont": 5.391263740817505e-05,
        "phi num": "071"
    },
    "072": {
        "cont": 0.0,
        "phi num": "072"
    },
    "073": {
        "cont": 4.331778903416724e-05,
        "phi num": "073"
    },
    "074": {
        "cont": 0.0,
        "phi num": "074"
    },
    "075": {
        "cont": -3.964210406178829e-05,
        "phi num": "075"
    },
    "076": {
        "cont": 0.0,
        "phi num": "076"
    },
    "077": {
        "cont": 0.0,
        "phi num": "077"
    },
    "078": {
        "cont": 6.101066174125635e-05,
        "phi num": "078"
    },
    "079": {
        "cont": 0.0,
        "phi num": "079"
    },
    "080": {
        "cont": 5.0755704426738794e-05,
        "phi num": "080"
    },
    "081": {
        "cont": 0.0,
        "phi num": "081"
    },
    "082": {
        "cont": 5.7948833754367326e-05,
        "phi num": "082"
    },
    "083": {
        "cont": 0.0,
        "phi num": "083"
    },
    "084": {
        "cont": 6.756642192453376e-05,
        "phi num": "084"
    },
    "085": {
        "cont": 0.00012301973565838873,
        "phi num": "085"
    },
    "086": {
        "cont": 5.405960037890505e-05,
        "phi num": "086"
    },
    "087": {
        "cont": 0.0,
        "phi num": "087"
    },
    "088": {
        "cont": 4.5717112099362334e-05,
        "phi num": "088"
    },
    "089": {
        "cont": 0.0,
        "phi num": "089"
    },
    "090": {
        "cont": 5.578214110307696e-05,
        "phi num": "090"
    },
    "091": {
        "cont": 0.0,
        "phi num": "091"
    },
    "092": {
        "cont": 6.183529804950295e-05,
        "phi num": "092"
    },
    "093": {
        "cont": 0.0,
        "phi num": "093"
    },
    "094": {
        "cont": 5.561408437001497e-05,
        "phi num": "094"
    },
    "095": {
        "cont": 0.0,
        "phi num": "095"
    },
    "096": {
        "cont": 0.0,
        "phi num": "096"
    },
    "097": {
        "cont": 7.53141960250883e-05,
        "phi num": "097"
    },
    "098": {
        "cont": 7.039230728609395e-05,
        "phi num": "098"
    },
    "099": {
        "cont": 0.0,
        "phi num": "099"
    }
}